.gitignore
MANIFEST.in
README.rst
setup.cfg
setup.py
docs/HISTORY.txt
raptus/__init__.py
raptus.inlinelightbox.egg-info/PKG-INFO
raptus.inlinelightbox.egg-info/SOURCES.txt
raptus.inlinelightbox.egg-info/dependency_links.txt
raptus.inlinelightbox.egg-info/entry_points.txt
raptus.inlinelightbox.egg-info/namespace_packages.txt
raptus.inlinelightbox.egg-info/not-zip-safe
raptus.inlinelightbox.egg-info/requires.txt
raptus.inlinelightbox.egg-info/top_level.txt
raptus/inlinelightbox/__init__.py
raptus/inlinelightbox/configure.zcml
raptus/inlinelightbox/browser/__init__.py
raptus/inlinelightbox/browser/blank.gif
raptus/inlinelightbox/browser/configure.zcml
raptus/inlinelightbox/browser/inlinelightbox.css
raptus/inlinelightbox/browser/inlinelightbox.init.js
raptus/inlinelightbox/browser/inlinelightbox.js
raptus/inlinelightbox/browser/loading.gif
raptus/inlinelightbox/browser/next.png
raptus/inlinelightbox/browser/prev.png
raptus/inlinelightbox/profiles/default/cssregistry.xml
raptus/inlinelightbox/profiles/default/jsregistry.xml
raptus/inlinelightbox/profiles/default/metadata.xml
raptus/inlinelightbox/profiles/default/propertiestool.xml
raptus/inlinelightbox/profiles/default/skins.xml
raptus/inlinelightbox/skins/raptus_inlinelightbox/inlinelightbox.settings.js.py