Metadata-Version: 1.0
Name: raptus.inlinelightbox
Version: 1.0b18
Summary: Provides an inline lightbox
Home-page: https://github.com/Raptus/raptus.inlinelightbox
Author: Raptus AG
Author-email: dev@raptus.com
License: GPL
Platform: UNKNOWN
Classifier: Programming Language :: Python
Classifier: Topic :: Software Development :: Libraries :: Python Modules
